pinax/__init__.py
pinax/templates/__init__.py
pinax/templates/apps.py
pinax/templates/locale/de/LC_MESSAGES/django.mo
pinax/templates/locale/de/LC_MESSAGES/django.po
pinax/templates/locale/fr/LC_MESSAGES/django.mo
pinax/templates/locale/fr/LC_MESSAGES/django.po
pinax/templates/locale/ja/LC_MESSAGES/django.mo
pinax/templates/locale/ja/LC_MESSAGES/django.po
pinax/templates/locale/zh_CN/LC_MESSAGES/django.mo
pinax/templates/locale/zh_CN/LC_MESSAGES/django.po
pinax/templates/management/__init__.py
pinax/templates/management/commands/__init__.py
pinax/templates/management/commands/copy_templates.py
pinax/templates/templates/404.html
pinax/templates/templates/500.html
pinax/templates/templates/_account_bar.html
pinax/templates/templates/_messages.html
pinax/templates/templates/_nav.html
pinax/templates/templates/base.html
pinax/templates/templates/site_base.html
pinax/templates/templates/subnav_base.html
pinax/templates/templates/account/base.html
pinax/templates/templates/account/delete.html
pinax/templates/templates/account/email_confirm.html
pinax/templates/templates/account/email_confirmation_sent.html
pinax/templates/templates/account/email_confirmed.html
pinax/templates/templates/account/login.html
pinax/templates/templates/account/logout.html
pinax/templates/templates/account/password_change.html
pinax/templates/templates/account/password_reset.html
pinax/templates/templates/account/password_reset_sent.html
pinax/templates/templates/account/password_reset_token.html
pinax/templates/templates/account/password_reset_token_fail.html
pinax/templates/templates/account/settings.html
pinax/templates/templates/account/signup.html
pinax/templates/templates/account/signup_closed.html
pinax/templates/templates/account/email/email_confirmation_message.txt
pinax/templates/templates/account/email/email_confirmation_subject.txt
pinax/templates/templates/account/email/invite_user.txt
pinax/templates/templates/account/email/invite_user_subject.txt
pinax_templates-3.0.0.dist-info/AUTHORS
pinax_templates-3.0.0.dist-info/LICENSE
pinax_templates-3.0.0.dist-info/METADATA
pinax_templates-3.0.0.dist-info/WHEEL
pinax_templates-3.0.0.dist-info/top_level.txt
pinax_templates-3.0.0.dist-info/RECORD
